vcdvcd/__init__.py
vcdvcd/vcdvcd.py
vcdvcd-2.5.0.data/scripts/vcdcat
vcdvcd-2.5.0.dist-info/LICENCE.md
vcdvcd-2.5.0.dist-info/METADATA
vcdvcd-2.5.0.dist-info/WHEEL
vcdvcd-2.5.0.dist-info/top_level.txt
vcdvcd-2.5.0.dist-info/RECORD
