Metadata-Version: 2.2
Name: vcdvcd
Version: 2.5.0
Summary: Python Verilog value change dump (VCD) parser library + the nifty vcdcat VCD command line viewer
Home-page: https://github.com/cirosantilli/vcdvcd
Author: Ciro Santilli
Author-email: ciro.santilli.contact@gmail.com
License-File: LICENCE.md
Dynamic: author
Dynamic: author-email
Dynamic: description
Dynamic: description-content-type
Dynamic: home-page
Dynamic: summary
